[
  {
    "transfermarktId": 492319,
    "fullName": "Franco Israel",
    "position": "GK",
    "detailedPosition": "GK",
    "jerseyNumber": null,
    "club": "Torino Calcio",
    "age": 26,
    "marketValueEur": 3000000,
    "photoUrl": "https://img.a.transfermarkt.technology/portrait/header/492319-1753680657.jpg?lm=1"
  },
  {
    "transfermarktId": 294843,
    "fullName": "Thiago Cardozo",
    "position": "GK",
    "detailedPosition": "GK",
    "jerseyNumber": null,
    "club": "Club Atlético Belgrano",
    "age": 29,
    "marketValueEur": 2700000,
    "photoUrl": "https://img.a.transfermarkt.technology/portrait/header/294843-1758833003.png?lm=1"
  },
  {
    "transfermarktId": 320739,
    "fullName": "Santiago Mele",
    "position": "GK",
    "detailedPosition": "GK",
    "jerseyNumber": null,
    "club": "Club de Fútbol Monterrey Rayados A.C",
    "age": 28,
    "marketValueEur": 2200000,
    "photoUrl": "https://img.a.transfermarkt.technology/portrait/header/320739-1766446350.jpg?lm=1"
  },
  {
    "transfermarktId": 264014,
    "fullName": "Sergio Rochet",
    "position": "GK",
    "detailedPosition": "GK",
    "jerseyNumber": null,
    "club": "Sport Club Internacional",
    "age": 33,
    "marketValueEur": 2000000,
    "photoUrl": "https://img.a.transfermarkt.technology/portrait/header/264014-1668501221.jpg?lm=1"
  },
  {
    "transfermarktId": 563089,
    "fullName": "Cristopher Fiermarín",
    "position": "GK",
    "detailedPosition": "GK",
    "jerseyNumber": null,
    "club": "Club Social y Deportivo Defensa y Justicia",
    "age": 28,
    "marketValueEur": 1500000,
    "photoUrl": "https://img.a.transfermarkt.technology/portrait/header/563089-1770652344.png?lm=1"
  },
  {
    "transfermarktId": 367651,
    "fullName": "Ignacio de Arruabarrena",
    "position": "GK",
    "detailedPosition": "GK",
    "jerseyNumber": null,
    "club": "Futebol Clube de Arouca",
    "age": 29,
    "marketValueEur": 1000000,
    "photoUrl": "https://img.a.transfermarkt.technology/portrait/header/367651-1692977383.jpg?lm=1"
  },
  {
    "transfermarktId": 465682,
    "fullName": "Mauro Silveira",
    "position": "GK",
    "detailedPosition": "GK",
    "jerseyNumber": null,
    "club": "Junior FC",
    "age": 25,
    "marketValueEur": 900000,
    "photoUrl": "https://img.a.transfermarkt.technology/portrait/header/465682-1752505115.JPG?lm=1"
  },
  {
    "transfermarktId": 58088,
    "fullName": "Fernando Muslera",
    "position": "GK",
    "detailedPosition": "GK",
    "jerseyNumber": null,
    "club": "Club Estudiantes de La Plata",
    "age": 39,
    "marketValueEur": 750000,
    "photoUrl": "https://img.a.transfermarkt.technology/portrait/header/58088-1671035581.png?lm=1"
  },
  {
    "transfermarktId": 612873,
    "fullName": "Renzo Bacchia",
    "position": "GK",
    "detailedPosition": "GK",
    "jerseyNumber": null,
    "club": "Asociación Atlética Estudiantes",
    "age": 27,
    "marketValueEur": 450000,
    "photoUrl": "https://img.a.transfermarkt.technology/portrait/header/612873-1642603874.JPG?lm=1"
  },
  {
    "transfermarktId": 368693,
    "fullName": "Francisco Tinaglini",
    "position": "GK",
    "detailedPosition": "GK",
    "jerseyNumber": null,
    "club": "Panserraikos Serres",
    "age": 27,
    "marketValueEur": 400000,
    "photoUrl": "https://img.a.transfermarkt.technology/portrait/header/368693-1742572102.png?lm=1"
  },
  {
    "transfermarktId": 572675,
    "fullName": "Maxi Araújo",
    "position": "DEF",
    "detailedPosition": "LB",
    "jerseyNumber": null,
    "club": "Sporting Clube de Portugal",
    "age": 26,
    "marketValueEur": 25000000,
    "photoUrl": "https://img.a.transfermarkt.technology/portrait/header/572675-1773786535.jpg?lm=1"
  },
  {
    "transfermarktId": 480267,
    "fullName": "Ronald Araujo",
    "position": "DEF",
    "detailedPosition": "CB",
    "jerseyNumber": null,
    "club": "Futbol Club Barcelona",
    "age": 27,
    "marketValueEur": 20000000,
    "photoUrl": "https://img.a.transfermarkt.technology/portrait/header/480267-1736431980.jpg?lm=1"
  },
  {
    "transfermarktId": 376514,
    "fullName": "Mathías Olivera",
    "position": "DEF",
    "detailedPosition": "LB",
    "jerseyNumber": null,
    "club": "SS Calcio Napoli",
    "age": 28,
    "marketValueEur": 15000000,
    "photoUrl": "https://img.a.transfermarkt.technology/portrait/header/376514-1681910576.jpg?lm=1"
  },
  {
    "transfermarktId": 250845,
    "fullName": "José María Giménez",
    "position": "DEF",
    "detailedPosition": "CB",
    "jerseyNumber": null,
    "club": "Atlético Madrid",
    "age": 31,
    "marketValueEur": 12000000,
    "photoUrl": "https://img.a.transfermarkt.technology/portrait/header/250845-1664970029.jpg?lm=1"
  },
  {
    "transfermarktId": 496268,
    "fullName": "Joaquín Piquerez",
    "position": "DEF",
    "detailedPosition": "LB",
    "jerseyNumber": null,
    "club": "Sociedade Esportiva Palmeiras",
    "age": 27,
    "marketValueEur": 12000000,
    "photoUrl": "https://img.a.transfermarkt.technology/portrait/header/496268-1706144655.jpg?lm=1"
  },
  {
    "transfermarktId": 438001,
    "fullName": "Santiago Bueno",
    "position": "DEF",
    "detailedPosition": "CB",
    "jerseyNumber": null,
    "club": "Wolverhampton Wanderers FC",
    "age": 27,
    "marketValueEur": 10000000,
    "photoUrl": "https://img.a.transfermarkt.technology/portrait/header/438001-1738823992.jpg?lm=1"
  },
  {
    "transfermarktId": 953901,
    "fullName": "Santiago Mouriño",
    "position": "DEF",
    "detailedPosition": "RB",
    "jerseyNumber": null,
    "club": "Villarreal Club de Fútbol",
    "age": 24,
    "marketValueEur": 10000000,
    "photoUrl": "https://img.a.transfermarkt.technology/portrait/header/953901-1691396102.jpg?lm=1"
  },
  {
    "transfermarktId": 577486,
    "fullName": "Gastón Álvarez",
    "position": "DEF",
    "detailedPosition": "CB",
    "jerseyNumber": null,
    "club": "Al-Qadsiah Saudi FC",
    "age": 26,
    "marketValueEur": 8000000,
    "photoUrl": "https://img.a.transfermarkt.technology/portrait/header/577486-1658904603.jpg?lm=1"
  },
  {
    "transfermarktId": 671479,
    "fullName": "Federico Pereira",
    "position": "DEF",
    "detailedPosition": "CB",
    "jerseyNumber": null,
    "club": "Deportivo Toluca Futbol Club",
    "age": 26,
    "marketValueEur": 6500000,
    "photoUrl": "https://img.a.transfermarkt.technology/portrait/header/671479-1683117674.JPG?lm=1"
  },
  {
    "transfermarktId": 446106,
    "fullName": "Juan Manuel Sanabria",
    "position": "DEF",
    "detailedPosition": "LB",
    "jerseyNumber": null,
    "club": "Real Salt Lake",
    "age": 26,
    "marketValueEur": 5500000,
    "photoUrl": "https://img.a.transfermarkt.technology/portrait/header/446106-1771718886.jpg?lm=1"
  },
  {
    "transfermarktId": 1228231,
    "fullName": "Juan Rodríguez",
    "position": "DEF",
    "detailedPosition": "CB",
    "jerseyNumber": null,
    "club": "Cagliari Calcio",
    "age": 20,
    "marketValueEur": 5000000,
    "photoUrl": "https://img.a.transfermarkt.technology/portrait/header/1228231-1767769559.jpg?lm=1"
  },
  {
    "transfermarktId": 552912,
    "fullName": "Bruno Méndez",
    "position": "DEF",
    "detailedPosition": "CB",
    "jerseyNumber": null,
    "club": "Deportivo Toluca Futbol Club",
    "age": 26,
    "marketValueEur": 5000000,
    "photoUrl": "https://img.a.transfermarkt.technology/portrait/header/552912-1558943297.png?lm=1"
  },
  {
    "transfermarktId": 852980,
    "fullName": "Nicolás Marichal",
    "position": "DEF",
    "detailedPosition": "CB",
    "jerseyNumber": null,
    "club": "FK Dinamo Moskva",
    "age": 25,
    "marketValueEur": 5000000,
    "photoUrl": "https://img.a.transfermarkt.technology/portrait/header/852980-1721727640.png?lm=1"
  },
  {
    "transfermarktId": 532389,
    "fullName": "Sebastián Cáceres",
    "position": "DEF",
    "detailedPosition": "CB",
    "jerseyNumber": null,
    "club": "CF América",
    "age": 26,
    "marketValueEur": 4500000,
    "photoUrl": "https://img.a.transfermarkt.technology/portrait/header/532389-1774479408.jpg?lm=1"
  },
  {
    "transfermarktId": 744324,
    "fullName": "Gastón Martirena",
    "position": "DEF",
    "detailedPosition": "RB",
    "jerseyNumber": null,
    "club": "Racing Club Asociación Civil de Avellaneda",
    "age": 26,
    "marketValueEur": 4500000,
    "photoUrl": "https://img.a.transfermarkt.technology/portrait/header/744324-1724348740.png?lm=1"
  },
  {
    "transfermarktId": 439072,
    "fullName": "Matías Viña",
    "position": "DEF",
    "detailedPosition": "LB",
    "jerseyNumber": null,
    "club": "Club Atlético River Plate",
    "age": 28,
    "marketValueEur": 4000000,
    "photoUrl": "https://img.a.transfermarkt.technology/portrait/header/439072-1663581362.jpg?lm=1"
  },
  {
    "transfermarktId": 216240,
    "fullName": "Lucas Olaza",
    "position": "DEF",
    "detailedPosition": "LB",
    "jerseyNumber": null,
    "club": "FK Krasnodar",
    "age": 31,
    "marketValueEur": 4000000,
    "photoUrl": "https://img.a.transfermarkt.technology/portrait/header/216240-1753530495.png?lm=1"
  },
  {
    "transfermarktId": 861981,
    "fullName": "Alan Matturro",
    "position": "DEF",
    "detailedPosition": "CB",
    "jerseyNumber": null,
    "club": "Levante Unión Deportiva",
    "age": 21,
    "marketValueEur": 4000000,
    "photoUrl": "https://img.a.transfermarkt.technology/portrait/header/861981-1692967519.jpg?lm=1"
  },
  {
    "transfermarktId": 665101,
    "fullName": "Leandro Lozano",
    "position": "DEF",
    "detailedPosition": "RB",
    "jerseyNumber": null,
    "club": "Asociación Atlética Argentinos Juniors",
    "age": 27,
    "marketValueEur": 4000000,
    "photoUrl": "https://img.a.transfermarkt.technology/portrait/header/665101-1719942158.png?lm=1"
  },
  {
    "transfermarktId": 732899,
    "fullName": "Guzmán Rodríguez",
    "position": "DEF",
    "detailedPosition": "CB",
    "jerseyNumber": null,
    "club": "Red Bull Bragantino",
    "age": 26,
    "marketValueEur": 4000000,
    "photoUrl": "https://img.a.transfermarkt.technology/portrait/header/732899-1721245448.jpg?lm=1"
  },
  {
    "transfermarktId": 577405,
    "fullName": "Mathías Laborda",
    "position": "DEF",
    "detailedPosition": "CB",
    "jerseyNumber": null,
    "club": "Vancouver Whitecaps FC",
    "age": 26,
    "marketValueEur": 3500000,
    "photoUrl": "https://img.a.transfermarkt.technology/portrait/header/577405-1771861630.jpg?lm=1"
  },
  {
    "transfermarktId": 102427,
    "fullName": "Sebastián Coates",
    "position": "DEF",
    "detailedPosition": "CB",
    "jerseyNumber": null,
    "club": "Sporting Clube de Portugal",
    "age": 35,
    "marketValueEur": 3500000,
    "photoUrl": "https://img.a.transfermarkt.technology/portrait/header/102427-1666100911.jpg?lm=1"
  },
  {
    "transfermarktId": 230552,
    "fullName": "Diego Laxalt",
    "position": "DEF",
    "detailedPosition": "LB",
    "jerseyNumber": null,
    "club": "FK Dinamo Moskva",
    "age": 33,
    "marketValueEur": 3000000,
    "photoUrl": "https://img.a.transfermarkt.technology/portrait/header/230552-1721727675.png?lm=1"
  },
  {
    "transfermarktId": 400661,
    "fullName": "Agustín Sant'Anna",
    "position": "DEF",
    "detailedPosition": "RB",
    "jerseyNumber": null,
    "club": "Red Bull Bragantino",
    "age": 28,
    "marketValueEur": 3000000,
    "photoUrl": "https://img.a.transfermarkt.technology/portrait/header/400661-1721919847.png?lm=1"
  },
  {
    "transfermarktId": 898352,
    "fullName": "Sebastián Boselli",
    "position": "DEF",
    "detailedPosition": "CB",
    "jerseyNumber": null,
    "club": "Getafe Club de Fútbol S. A. D. Team Dubai",
    "age": 22,
    "marketValueEur": 2800000,
    "photoUrl": "https://img.a.transfermarkt.technology/portrait/header/898352-1739826537.jpg?lm=1"
  },
  {
    "transfermarktId": 589363,
    "fullName": "Agustín Oliveros",
    "position": "DEF",
    "detailedPosition": "CB",
    "jerseyNumber": null,
    "club": "Impulsora del Deportivo Necaxa",
    "age": 27,
    "marketValueEur": 2800000,
    "photoUrl": "https://img.a.transfermarkt.technology/portrait/header/589363-1623093589.jpg?lm=1"
  },
  {
    "transfermarktId": 339699,
    "fullName": "Giovanni González",
    "position": "DEF",
    "detailedPosition": "RB",
    "jerseyNumber": null,
    "club": "FK Krasnodar",
    "age": 31,
    "marketValueEur": 2500000,
    "photoUrl": "https://img.a.transfermarkt.technology/portrait/header/339699-1753530559.png?lm=1"
  },
  {
    "transfermarktId": 373916,
    "fullName": "Marcelo Saracchi",
    "position": "DEF",
    "detailedPosition": "LB",
    "jerseyNumber": null,
    "club": "Celtic FC",
    "age": 28,
    "marketValueEur": 2000000,
    "photoUrl": "https://img.a.transfermarkt.technology/portrait/header/373916-1739889186.jpg?lm=1"
  },
  {
    "transfermarktId": 856047,
    "fullName": "Mateo Ponte",
    "position": "DEF",
    "detailedPosition": "RB",
    "jerseyNumber": null,
    "club": "S. A. F. Botafogo",
    "age": 22,
    "marketValueEur": 2000000,
    "photoUrl": "https://img.a.transfermarkt.technology/portrait/header/856047-1676634597.jpg?lm=1"
  },
  {
    "transfermarktId": 437993,
    "fullName": "Maximiliano Falcón",
    "position": "DEF",
    "detailedPosition": "CB",
    "jerseyNumber": null,
    "club": "Club Internacional de Fútbol Miami",
    "age": 29,
    "marketValueEur": 1800000,
    "photoUrl": "https://img.a.transfermarkt.technology/portrait/header/437993-1771694584.jpg?lm=1"
  },
  {
    "transfermarktId": 369081,
    "fullName": "Federico Valverde",
    "position": "MID",
    "detailedPosition": "CM",
    "jerseyNumber": null,
    "club": "Real Madrid Club de Fútbol",
    "age": 27,
    "marketValueEur": 120000000,
    "photoUrl": "https://img.a.transfermarkt.technology/portrait/header/369081-1731018042.jpg?lm=1"
  },
  {
    "transfermarktId": 476701,
    "fullName": "Manuel Ugarte",
    "position": "MID",
    "detailedPosition": "CDM",
    "jerseyNumber": null,
    "club": "Manchester United FC",
    "age": 25,
    "marketValueEur": 30000000,
    "photoUrl": "https://img.a.transfermarkt.technology/portrait/header/476701-1715107512.jpg?lm=1"
  },
  {
    "transfermarktId": 354362,
    "fullName": "Rodrigo Bentancur",
    "position": "MID",
    "detailedPosition": "CDM",
    "jerseyNumber": null,
    "club": "Tottenham Hotspur FC",
    "age": 28,
    "marketValueEur": 22000000,
    "photoUrl": "https://img.a.transfermarkt.technology/portrait/header/354362-1740605779.jpg?lm=1"
  },
  {
    "transfermarktId": 606752,
    "fullName": "Rodrigo Zalazar",
    "position": "MID",
    "detailedPosition": "CM",
    "jerseyNumber": null,
    "club": "Sporting Clube de Braga",
    "age": 26,
    "marketValueEur": 22000000,
    "photoUrl": "https://img.a.transfermarkt.technology/portrait/header/606752-1771936397.png?lm=1"
  },
  {
    "transfermarktId": 248410,
    "fullName": "Giorgian de Arrascaeta",
    "position": "MID",
    "detailedPosition": "CAM",
    "jerseyNumber": null,
    "club": "Clube de Regatas do Flamengo",
    "age": 31,
    "marketValueEur": 15000000,
    "photoUrl": "https://img.a.transfermarkt.technology/portrait/header/248410-1668501457.jpg?lm=1"
  },
  {
    "transfermarktId": 318077,
    "fullName": "Lucas Torreira",
    "position": "MID",
    "detailedPosition": "CDM",
    "jerseyNumber": null,
    "club": "Galatasaray Spor Kulübü",
    "age": 30,
    "marketValueEur": 12000000,
    "photoUrl": "https://img.a.transfermarkt.technology/portrait/header/318077-1671110829.png?lm=1"
  },
  {
    "transfermarktId": 290249,
    "fullName": "Mauro Arambarri",
    "position": "MID",
    "detailedPosition": "CM",
    "jerseyNumber": null,
    "club": "Getafe Club de Fútbol S. A. D. Team Dubai",
    "age": 30,
    "marketValueEur": 10000000,
    "photoUrl": "https://img.a.transfermarkt.technology/portrait/header/290249-1669365106.jpg?lm=1"
  },
  {
    "transfermarktId": 397458,
    "fullName": "Nicolás de la Cruz",
    "position": "MID",
    "detailedPosition": "CM",
    "jerseyNumber": null,
    "club": "Clube de Regatas do Flamengo",
    "age": 28,
    "marketValueEur": 9000000,
    "photoUrl": "https://img.a.transfermarkt.technology/portrait/header/397458-1719565799.jpg?lm=1"
  },
  {
    "transfermarktId": 317454,
    "fullName": "Diego Rossi",
    "position": "MID",
    "detailedPosition": "CAM",
    "jerseyNumber": null,
    "club": "Columbus Crew",
    "age": 28,
    "marketValueEur": 8500000,
    "photoUrl": "https://img.a.transfermarkt.technology/portrait/header/317454-1771600111.jpg?lm=1"
  },
  {
    "transfermarktId": 707447,
    "fullName": "Emiliano Martínez",
    "position": "MID",
    "detailedPosition": "CDM",
    "jerseyNumber": null,
    "club": "Sociedade Esportiva Palmeiras",
    "age": 26,
    "marketValueEur": 8000000,
    "photoUrl": "https://img.a.transfermarkt.technology/portrait/header/707447-1720681061.jpg?lm=1"
  },
  {
    "transfermarktId": 898350,
    "fullName": "Facundo Bernal",
    "position": "MID",
    "detailedPosition": "CDM",
    "jerseyNumber": null,
    "club": "Fluminense FC",
    "age": 22,
    "marketValueEur": 6000000,
    "photoUrl": "https://img.a.transfermarkt.technology/portrait/header/898350-1721081696.jpg?lm=1"
  },
  {
    "transfermarktId": 465819,
    "fullName": "Santiago Rodríguez",
    "position": "MID",
    "detailedPosition": "CAM",
    "jerseyNumber": null,
    "club": "S. A. F. Botafogo",
    "age": 26,
    "marketValueEur": 6000000,
    "photoUrl": "https://img.a.transfermarkt.technology/portrait/header/465819-1710583524.jpg?lm=1"
  },
  {
    "transfermarktId": 881645,
    "fullName": "Ignacio Sosa",
    "position": "MID",
    "detailedPosition": "CM",
    "jerseyNumber": null,
    "club": "Red Bull Bragantino",
    "age": 22,
    "marketValueEur": 5000000,
    "photoUrl": "https://img.a.transfermarkt.technology/portrait/header/881645-1721247467.jpg?lm=1"
  },
  {
    "transfermarktId": 315063,
    "fullName": "Nahitan Nández",
    "position": "MID",
    "detailedPosition": "CM",
    "jerseyNumber": null,
    "club": "Al-Qadsiah Saudi FC",
    "age": 30,
    "marketValueEur": 4500000,
    "photoUrl": "https://img.a.transfermarkt.technology/portrait/header/315063-1686126135.jpg?lm=1"
  },
  {
    "transfermarktId": 310744,
    "fullName": "Fernando Gorriarán",
    "position": "MID",
    "detailedPosition": "CM",
    "jerseyNumber": null,
    "club": "Club Tigres UANL Sinergia Deportiva",
    "age": 31,
    "marketValueEur": 4000000,
    "photoUrl": "https://img.a.transfermarkt.technology/portrait/header/310744-1581594167.png?lm=1"
  },
  {
    "transfermarktId": 625569,
    "fullName": "Nicolás Acevedo",
    "position": "MID",
    "detailedPosition": "CDM",
    "jerseyNumber": null,
    "club": "Esporte Clube Bahia",
    "age": 27,
    "marketValueEur": 4000000,
    "photoUrl": "https://img.a.transfermarkt.technology/portrait/header/625569-1748913870.jpg?lm=1"
  },
  {
    "transfermarktId": 997827,
    "fullName": "Thiago Helguera",
    "position": "MID",
    "detailedPosition": "CDM",
    "jerseyNumber": null,
    "club": "Sporting Clube de Braga",
    "age": 20,
    "marketValueEur": 3500000,
    "photoUrl": "https://img.a.transfermarkt.technology/portrait/header/default.jpg?lm=1"
  },
  {
    "transfermarktId": 690533,
    "fullName": "César Araújo",
    "position": "MID",
    "detailedPosition": "CDM",
    "jerseyNumber": null,
    "club": "Club Tigres UANL Sinergia Deportiva",
    "age": 25,
    "marketValueEur": 3500000,
    "photoUrl": "https://img.a.transfermarkt.technology/portrait/header/690533-1740779724.jpg?lm=1"
  },
  {
    "transfermarktId": 1220232,
    "fullName": "Lucas Sanabria",
    "position": "MID",
    "detailedPosition": "CDM",
    "jerseyNumber": null,
    "club": "Los Angeles Galaxy",
    "age": 22,
    "marketValueEur": 3500000,
    "photoUrl": "https://img.a.transfermarkt.technology/portrait/header/1220232-1771693654.jpg?lm=1"
  },
  {
    "transfermarktId": 462070,
    "fullName": "Nicolás Fonseca",
    "position": "MID",
    "detailedPosition": "CDM",
    "jerseyNumber": null,
    "club": "Real Oviedo",
    "age": 27,
    "marketValueEur": 3000000,
    "photoUrl": "https://img.a.transfermarkt.technology/portrait/header/462070-1721920695.png?lm=1"
  },
  {
    "transfermarktId": 465817,
    "fullName": "Alan Rodríguez",
    "position": "MID",
    "detailedPosition": "CM",
    "jerseyNumber": null,
    "club": "Sport Club Internacional",
    "age": 26,
    "marketValueEur": 2300000,
    "photoUrl": "https://img.a.transfermarkt.technology/portrait/header/465817-1720123027.png?lm=1"
  },
  {
    "transfermarktId": 131109,
    "fullName": "Gastón Brugman",
    "position": "MID",
    "detailedPosition": "CDM",
    "jerseyNumber": null,
    "club": "Nashville SC",
    "age": 33,
    "marketValueEur": 2000000,
    "photoUrl": "https://img.a.transfermarkt.technology/portrait/header/131109-1740672677.jpg?lm=1"
  },
  {
    "transfermarktId": 803018,
    "fullName": "Joaquín Valiente",
    "position": "MID",
    "detailedPosition": "CAM",
    "jerseyNumber": null,
    "club": "FC Dallas",
    "age": 25,
    "marketValueEur": 1800000,
    "photoUrl": "https://img.a.transfermarkt.technology/portrait/header/803018-1739571850.JPG?lm=1"
  },
  {
    "transfermarktId": 143812,
    "fullName": "Matías Vecino",
    "position": "MID",
    "detailedPosition": "CM",
    "jerseyNumber": null,
    "club": "Real Club Celta de Vigo S. A. D",
    "age": 34,
    "marketValueEur": 1500000,
    "photoUrl": "https://img.a.transfermarkt.technology/portrait/header/143812-1695026891.jpg?lm=1"
  },
  {
    "transfermarktId": 895679,
    "fullName": "Santiago Homenchenko",
    "position": "MID",
    "detailedPosition": "CDM",
    "jerseyNumber": null,
    "club": "Querétaro Fútbol Club",
    "age": 22,
    "marketValueEur": 1500000,
    "photoUrl": "https://img.a.transfermarkt.technology/portrait/header/895679-1688497587.jpg?lm=1"
  },
  {
    "transfermarktId": 221805,
    "fullName": "Ignacio Rivero",
    "position": "MID",
    "detailedPosition": "CM",
    "jerseyNumber": null,
    "club": "Club Tijuana Xoloitzcuintles de Caliente",
    "age": 34,
    "marketValueEur": 1500000,
    "photoUrl": "https://img.a.transfermarkt.technology/portrait/header/221805-1565169333.png?lm=1"
  },
  {
    "transfermarktId": 733083,
    "fullName": "Nicolás Quagliata",
    "position": "MID",
    "detailedPosition": "CAM",
    "jerseyNumber": null,
    "club": "Club Atlético Central Córdoba",
    "age": 26,
    "marketValueEur": 1500000,
    "photoUrl": "https://img.a.transfermarkt.technology/portrait/header/733083-1762995953.JPG?lm=1"
  },
  {
    "transfermarktId": 563812,
    "fullName": "Christian Oliva",
    "position": "MID",
    "detailedPosition": "CDM",
    "jerseyNumber": null,
    "club": "Santos Futebol Clube",
    "age": 29,
    "marketValueEur": 1400000,
    "photoUrl": "https://img.a.transfermarkt.technology/portrait/header/563812-1719944060.png?lm=1"
  },
  {
    "transfermarktId": 454181,
    "fullName": "Gabriel Neves",
    "position": "MID",
    "detailedPosition": "CDM",
    "jerseyNumber": null,
    "club": "Club Estudiantes de La Plata",
    "age": 28,
    "marketValueEur": 1300000,
    "photoUrl": "https://img.a.transfermarkt.technology/portrait/header/454181-1720465312.png?lm=1"
  },
  {
    "transfermarktId": 322696,
    "fullName": "Facundo Waller",
    "position": "MID",
    "detailedPosition": "LM",
    "jerseyNumber": null,
    "club": "Club Atlético Huracán",
    "age": 29,
    "marketValueEur": 1200000,
    "photoUrl": "https://img.a.transfermarkt.technology/portrait/header/322696-1755535526.png?lm=1"
  },
  {
    "transfermarktId": 431190,
    "fullName": "Carlos Protesoni",
    "position": "MID",
    "detailedPosition": "CDM",
    "jerseyNumber": null,
    "club": "Deportivo Alavés S. A. D",
    "age": 28,
    "marketValueEur": 1000000,
    "photoUrl": "https://img.a.transfermarkt.technology/portrait/header/431190-1635923163.JPG?lm=1"
  },
  {
    "transfermarktId": 261309,
    "fullName": "David Terans",
    "position": "MID",
    "detailedPosition": "CAM",
    "jerseyNumber": null,
    "club": "Fluminense FC",
    "age": 31,
    "marketValueEur": 1000000,
    "photoUrl": "https://img.a.transfermarkt.technology/portrait/header/261309-1742486760.jpg?lm=1"
  },
  {
    "transfermarktId": 555194,
    "fullName": "Mathías Tomás",
    "position": "MID",
    "detailedPosition": "CAM",
    "jerseyNumber": null,
    "club": "Panserraikos Serres",
    "age": 25,
    "marketValueEur": 900000,
    "photoUrl": "https://img.a.transfermarkt.technology/portrait/header/555194-1730218054.jpg?lm=1"
  },
  {
    "transfermarktId": 546543,
    "fullName": "Darwin Núñez",
    "position": "FWD",
    "detailedPosition": "ST",
    "jerseyNumber": null,
    "club": "Al-Hilal Saudi FC",
    "age": 26,
    "marketValueEur": 25000000,
    "photoUrl": "https://img.a.transfermarkt.technology/portrait/header/546543-1681827179.jpg?lm=1"
  },
  {
    "transfermarktId": 465822,
    "fullName": "Facundo Torres",
    "position": "FWD",
    "detailedPosition": "RW",
    "jerseyNumber": null,
    "club": "Austin FC",
    "age": 26,
    "marketValueEur": 13000000,
    "photoUrl": "https://img.a.transfermarkt.technology/portrait/header/465822-1773849110.jpg?lm=1"
  },
  {
    "transfermarktId": 856143,
    "fullName": "Luciano Rodríguez",
    "position": "FWD",
    "detailedPosition": "ST",
    "jerseyNumber": null,
    "club": "Neom Sports Club",
    "age": 22,
    "marketValueEur": 10000000,
    "photoUrl": "https://img.a.transfermarkt.technology/portrait/header/856143-1718703439.jpg?lm=1"
  },
  {
    "transfermarktId": 611426,
    "fullName": "Matías Arezo",
    "position": "FWD",
    "detailedPosition": "ST",
    "jerseyNumber": null,
    "club": "Grêmio Foot-Ball Porto Alegrense",
    "age": 23,
    "marketValueEur": 7000000,
    "photoUrl": "https://img.a.transfermarkt.technology/portrait/header/611426-1758911319.jpg?lm=1"
  },
  {
    "transfermarktId": 465818,
    "fullName": "Brian Rodríguez",
    "position": "FWD",
    "detailedPosition": "LW",
    "jerseyNumber": null,
    "club": "CF América",
    "age": 25,
    "marketValueEur": 6500000,
    "photoUrl": "https://img.a.transfermarkt.technology/portrait/header/465818-1646496779.jpg?lm=1"
  },
  {
    "transfermarktId": 676318,
    "fullName": "Facundo Pellistri",
    "position": "FWD",
    "detailedPosition": "RW",
    "jerseyNumber": null,
    "club": "Panathinaikos Athlitikos Omilos",
    "age": 24,
    "marketValueEur": 6000000,
    "photoUrl": "https://img.a.transfermarkt.technology/portrait/header/676318-1756043624.png?lm=1"
  },
  {
    "transfermarktId": 457533,
    "fullName": "Agustín Canobbio",
    "position": "FWD",
    "detailedPosition": "LW",
    "jerseyNumber": null,
    "club": "Fluminense FC",
    "age": 27,
    "marketValueEur": 6000000,
    "photoUrl": "https://img.a.transfermarkt.technology/portrait/header/457533-1713630231.jpg?lm=1"
  },
  {
    "transfermarktId": 640109,
    "fullName": "Martín Satriano",
    "position": "FWD",
    "detailedPosition": "ST",
    "jerseyNumber": null,
    "club": "Getafe Club de Fútbol S. A. D. Team Dubai",
    "age": 25,
    "marketValueEur": 6000000,
    "photoUrl": "https://img.a.transfermarkt.technology/portrait/header/640109-1626685122.jpg?lm=1"
  },
  {
    "transfermarktId": 481367,
    "fullName": "Miguel Merentiel",
    "position": "FWD",
    "detailedPosition": "ST",
    "jerseyNumber": null,
    "club": "Club Atlético Boca Juniors",
    "age": 30,
    "marketValueEur": 5500000,
    "photoUrl": "https://img.a.transfermarkt.technology/portrait/header/481367-1739899560.jpg?lm=1"
  },
  {
    "transfermarktId": 657746,
    "fullName": "Cristian Olivera",
    "position": "FWD",
    "detailedPosition": "RW",
    "jerseyNumber": null,
    "club": "Esporte Clube Bahia",
    "age": 24,
    "marketValueEur": 5000000,
    "photoUrl": "https://img.a.transfermarkt.technology/portrait/header/657746-1709932388.jpg?lm=1"
  },
  {
    "transfermarktId": 948275,
    "fullName": "Álvaro Rodríguez",
    "position": "FWD",
    "detailedPosition": "ST",
    "jerseyNumber": null,
    "club": "Elche Club de Fútbol",
    "age": 21,
    "marketValueEur": 5000000,
    "photoUrl": "https://img.a.transfermarkt.technology/portrait/header/948275-1660124773.jpg?lm=1"
  },
  {
    "transfermarktId": 812625,
    "fullName": "Agustín Álvarez",
    "position": "FWD",
    "detailedPosition": "ST",
    "jerseyNumber": null,
    "club": "AC Monza",
    "age": 24,
    "marketValueEur": 4500000,
    "photoUrl": "https://img.a.transfermarkt.technology/portrait/header/812625-1704205457.jpg?lm=1"
  },
  {
    "transfermarktId": 755457,
    "fullName": "Tiago Palacios",
    "position": "FWD",
    "detailedPosition": "RW",
    "jerseyNumber": null,
    "club": "Club Estudiantes de La Plata",
    "age": 25,
    "marketValueEur": 4500000,
    "photoUrl": "https://img.a.transfermarkt.technology/portrait/header/755457-1739827666.jpg?lm=1"
  },
  {
    "transfermarktId": 280795,
    "fullName": "Jonathan Rodríguez",
    "position": "FWD",
    "detailedPosition": "ST",
    "jerseyNumber": null,
    "club": "Portland Timbers",
    "age": 32,
    "marketValueEur": 4000000,
    "photoUrl": "https://img.a.transfermarkt.technology/portrait/header/280795-1740822087.jpg?lm=1"
  },
  {
    "transfermarktId": 578419,
    "fullName": "Federico Viñas",
    "position": "FWD",
    "detailedPosition": "ST",
    "jerseyNumber": null,
    "club": "Real Oviedo",
    "age": 27,
    "marketValueEur": 4000000,
    "photoUrl": "https://img.a.transfermarkt.technology/portrait/header/578419-1763542136.jpg?lm=1"
  },
  {
    "transfermarktId": 743951,
    "fullName": "Thiago Borbas",
    "position": "FWD",
    "detailedPosition": "ST",
    "jerseyNumber": null,
    "club": "Real Oviedo",
    "age": 24,
    "marketValueEur": 4000000,
    "photoUrl": "https://img.a.transfermarkt.technology/portrait/header/743951-1649428213.JPG?lm=1"
  },
  {
    "transfermarktId": 928647,
    "fullName": "Matías Abaldo",
    "position": "FWD",
    "detailedPosition": "LW",
    "jerseyNumber": null,
    "club": "Club Atlético Independiente de Avellaneda",
    "age": 22,
    "marketValueEur": 3500000,
    "photoUrl": "https://img.a.transfermarkt.technology/portrait/header/928647-1743016476.jpg?lm=1"
  },
  {
    "transfermarktId": 895926,
    "fullName": "Joaquín Lavega",
    "position": "FWD",
    "detailedPosition": "LW",
    "jerseyNumber": null,
    "club": "Coritiba Foot Ball Club",
    "age": 21,
    "marketValueEur": 3000000,
    "photoUrl": "https://img.a.transfermarkt.technology/portrait/header/895926-1720819944.jpg?lm=1"
  },
  {
    "transfermarktId": 189410,
    "fullName": "Rodrigo Aguirre",
    "position": "FWD",
    "detailedPosition": "ST",
    "jerseyNumber": null,
    "club": "Club Tigres UANL Sinergia Deportiva",
    "age": 31,
    "marketValueEur": 2500000,
    "photoUrl": "https://img.a.transfermarkt.technology/portrait/header/189410-1449133224.jpg?lm=1"
  },
  {
    "transfermarktId": 454625,
    "fullName": "Matías Cóccaro",
    "position": "FWD",
    "detailedPosition": "ST",
    "jerseyNumber": null,
    "club": "Club Atlético Newell’s Old Boys",
    "age": 28,
    "marketValueEur": 2500000,
    "photoUrl": "https://img.a.transfermarkt.technology/portrait/header/454625-1710100418.jpg?lm=1"
  },
  {
    "transfermarktId": 577489,
    "fullName": "Emiliano Gómez",
    "position": "FWD",
    "detailedPosition": "SS",
    "jerseyNumber": null,
    "club": "CF Puebla de La Franja",
    "age": 24,
    "marketValueEur": 2500000,
    "photoUrl": "https://img.a.transfermarkt.technology/portrait/header/577489-1721317803.png?lm=1"
  },
  {
    "transfermarktId": 1110360,
    "fullName": "Bruno Damiani",
    "position": "FWD",
    "detailedPosition": "ST",
    "jerseyNumber": null,
    "club": "Philadelphia Union",
    "age": 24,
    "marketValueEur": 2500000,
    "photoUrl": "https://img.a.transfermarkt.technology/portrait/header/1110360-1771713729.jpg?lm=1"
  },
  {
    "transfermarktId": 482144,
    "fullName": "Michel Araújo",
    "position": "FWD",
    "detailedPosition": "RW",
    "jerseyNumber": null,
    "club": "Esporte Clube Bahia",
    "age": 29,
    "marketValueEur": 2500000,
    "photoUrl": "https://img.a.transfermarkt.technology/portrait/header/482144-1748913974.jpg?lm=1"
  },
  {
    "transfermarktId": 1104206,
    "fullName": "Agustín Albarracín",
    "position": "FWD",
    "detailedPosition": "LW",
    "jerseyNumber": null,
    "club": "Cagliari Calcio",
    "age": 20,
    "marketValueEur": 2300000,
    "photoUrl": "https://img.a.transfermarkt.technology/portrait/header/1104206-1769528142.png?lm=1"
  },
  {
    "transfermarktId": 973805,
    "fullName": "Andrés Ferrari",
    "position": "FWD",
    "detailedPosition": "ST",
    "jerseyNumber": null,
    "club": "Koninklijke Sint-Truidense Voetbalvereniging",
    "age": 23,
    "marketValueEur": 2200000,
    "photoUrl": "https://img.a.transfermarkt.technology/portrait/header/973805-1682362275.jpeg?lm=1"
  },
  {
    "transfermarktId": 694157,
    "fullName": "Diego Abreu",
    "position": "FWD",
    "detailedPosition": "ST",
    "jerseyNumber": null,
    "club": "Club Tijuana Xoloitzcuintles de Caliente",
    "age": 22,
    "marketValueEur": 2000000,
    "photoUrl": "https://img.a.transfermarkt.technology/portrait/header/694157-1743017191.jpg?lm=1"
  },
  {
    "transfermarktId": 928648,
    "fullName": "Anderson Duarte",
    "position": "FWD",
    "detailedPosition": "RW",
    "jerseyNumber": null,
    "club": "Club Atlético de San Luis",
    "age": 22,
    "marketValueEur": 2000000,
    "photoUrl": "https://img.a.transfermarkt.technology/portrait/header/928648-1721081277.jpg?lm=1"
  }
]
